projectsmigrator.py
projectsmigrator-0.0.2.dist-info/entry_points.txt
projectsmigrator-0.0.2.dist-info/LICENSE
projectsmigrator-0.0.2.dist-info/WHEEL
projectsmigrator-0.0.2.dist-info/METADATA
projectsmigrator-0.0.2.dist-info/RECORD
