Metadata-Version: 2.1
Name: projectsmigrator
Version: 0.0.2
Summary: Migrates one or more ZenHub workspaces to a Github Project
Keywords: github,project management,zenhub,migration,sync
Author-email: Dylan Jay <software@pretagov.com>
Requires-Python: >=3.7
Classifier: License :: OSI Approved :: MIT License
Classifier: Operating System :: OS Independent
Classifier: Programming Language :: Python :: 3
Classifier: Programming Language :: Python :: 3.7
Classifier: Programming Language :: Python :: 3.8
Classifier: Programming Language :: Python :: 3.9
Classifier: Programming Language :: Python :: 3.10
Classifier: Programming Language :: Python :: 3.11
Requires-Dist: requests>2
Requires-Dist: gql
Requires-Dist: aiohttp
Requires-Dist: docopt
Project-URL: Bug Tracker, https://github.com/pretagov/projectsmigrator/issues
Project-URL: Homepage, https://github.com/pretagov/projectsmigrator
Project-URL: changelog, https://github.com/pretagov/projectsmigrator/blob/master/CHANGELOG.md
